{
  "brand": {
    "logo": {
      "src": "/images/Rolaids-logo-415x114.png"
    }
  },
  "nav": {
    "primary": [
      {
        "label": "Products",
        "url": "products.html",
        "dropdownMenu": [
          {
            "label": "Advanced Tablets",
            "url": "#advanced-tablet",
            "image": {
              "src": "/images/Rolaids-products-drop-adv.png"
            }
          },
          {
            "label": "Regular Tablets",
            "url": "#regular-tablet",
            "image": {
              "src": "/images/Rolaids-products-drop-reg.png"
            }
          },
          {
            "label": "Ultimate Tablets",
            "url": "#ultimate-tablet",
            "image": {
              "src": "/images/Rolaids-products-drop-ult.png"
            }
          },
          {
            "label": "Extra Strength Tablets",
            "url": "#extra-strength-tablet",
            "image": {
              "src": "/images/Rolaids-products-drop-xtra.png"
            }
          }
        ]
      },
      {
        "label": "The Rolaids Advantage",
        "url": "/rolaids-advantage.html"
      },
      {
        "label": "Symptoms",
        "url": "#symptoms",
        "dropdownMenu": [
          {
            "label": "Heartburn",
            "url": "heartburn.html",
            "image": {
              "src": "/images/Rolaids-symptoms-heartburn.png"
            }
          },
          {
            "label": "Gas",
            "url": "#gas",
            "image": {
              "src": "/images/Rolaids-symptoms-gas.png"
            }
          },
          {
            "label": "Indigestion",
            "url": "#indigestion",
            "image": {
              "src": "/images/Rolaids-symptoms-indigestion.png"
            }
          }
        ]
      },
      {
        "label": "Coupons & Offers",
        "url": "/coupon.html"
      }
    ],
    "secondary": [
      {
        "label": "contact us",
        "url": "/contact.html"
      },
      {
        "label": "where to buy",
        "url": "/where-to-buy.html"
      }
    ]
  },
  "socialLinks": [
    {
      "id": "twitter",
      "title": "Twitter",
      "url": "https://twitter.com/rolaids"
    },
    {
      "id": "facebook",
      "title": "Facebook",
      "url": "https://www.facebook.com/rolaids"
    },
    {
      "id": "instagram",
      "title": "Instagram",
      "url": "https://instagram.com/rolaids"
    }
  ],
  "page": {
    "home": {
      "carousel": [
        {
          "src": "https://skyfiregcs-a.akamaihd.net/exp=1457561872~acl=%2A%2F494631530.mp4%2A~hmac=6f34d833a18d116ef000f514e581c0dbb0782d588fec1293b37556446ea0974a/2tierchgci/vimeo-prod-skyfire-std-us/01/1673/6/158368523/494631530.mp4",
          "caption": {
            "title": "Headline 1 Goes Here",
            "text": "Consectetur eaque magni fuga modi harum quam sequi officiis explicabo asperiores libero. Ratione eligendi placeat.",
            "buttonLink": "#",
            "buttonText": "Learn More"
          }
        }
      ],
      "coupon": {
        "text": "Save $1.00 on any Rolaids product"
      },
      "callout": {
        "first": {
          "backgroundImage": "http://lorempixel.com/800/800/cats",
          "title": "Kick Acid And Gas",
          "button1": {
            "text": "Learn More",
            "link": "#"
          },
          "button2": {
            "text": "Watch The Video",
            "link": "#"
          }
        },
        "last": {
          "backgroundImage": "http://lorempixel.com/800/800/cats",
          "text": "Rolaids Regular Strength Tablets <span class=\"text-emphasis--secondary\">Neutralize 44% More Acid</span> Than Tums Regular"
        }
      }
    },
    "product": {
      "hero": {
        "backgroundImage": {
          "src": "//placehold.it/1200x800"
        },
        "caption": {
          "title": "Rolaids<br>Advanced&reg; Tablets",
          "text": "It kicks acid and a whole lot more"
        },
        "product": {
          "large": {
            "src": "//placehold.it/350/f0f0f0"
          },
          "small": {
            "src": "//placehold.it/300x100/cfcfcf"
          }
        }
      }
    },
    "symptom": {
      "hero": {
        "backgroundImage": {
          "src": "//placehold.it/1200x800"
        },
        "caption": {
          "title": "Heartburn",
          "text": "That burning sensation in your throat caused by stomach acid backing up into your esophagus. Ouch."
        }
      },
      "section": [
        {
          "class": "section-triangle",
          "nav": {
            "link": "#what-is-heartburn",
            "label": "What is Heartburn?"
          },
          "content": {
            "title": "What is Heartburn?",
            "subtitle": "Overview",
            "text": "Nothing can ruin a good time faster than heartburn.",
            "image": {
              "src": "//lorempixel.com/800/600/sports"
            }
          }
        },
        {
          "class": "section-display",
          "nav": {
            "link": "#what-are-the-symptoms",
            "label": "What are the symptoms of Heartburn?"
          },
          "content": {
            "title": "Heartburn Symptoms",
            "subtitle": "Symptoms",
            "text": "The primary symptom of heartburn is a painful, burning sensaiton in the chest",
            "image": {
              "src": "//lorempixel.com/800/600"
            }
          }
        },
        {
          "nav": {
            "link": "#what-triggers-heartburn",
            "label": "What triggers Heartburn?"
          }
        },
        {
          "nav": {
            "link": "#what-prevents-heartburn",
            "label": "What can I do to help prevent Heartburn?"
          }
        }
      ]
    },
    "coupon": {
      "hero": {
        "backgroundImage": {
          "src": "//placehold.it/1200x800"
        }
      },
      "content": {
        "title": "Save $1.00 on Rolaids&reg;",
        "text": "",
        "button": {
          "text": "Download Coupon",
          "buttonLink": "#"
        },
        "image": {
          "src": "//placehold.it/500x500/ffffff",
          "alt": "Image Alt"
        }
      }
    },
    "contact": {
      "hero": {
        "backgroundImage": {
          "src": "http://placehold.it/1200x800"
        },
        "caption": {
          "title": "Contact Us"
        }
      },
      "productImage": {
        "src": "http://placehold.it/500/ffffff"
      }
    }
  }
}
